tutormagic.py
tutormagic-0.3.1.dist-info/LICENSE
tutormagic-0.3.1.dist-info/METADATA
tutormagic-0.3.1.dist-info/WHEEL
tutormagic-0.3.1.dist-info/top_level.txt
tutormagic-0.3.1.dist-info/RECORD
