Metadata-Version: 2.1
Name: tutormagic
Version: 0.3.1
Summary: Magic to display pythontutor.com from a code cell in the IPython notebook.
Home-page: https://github.com/kikocorreoso/tutormagic
Author: Kikocorreoso
Author-email: UNKNOWN
License: MIT
Keywords: ipython jupyter notebook pythontutor.com teaching
Platform: UNKNOWN
Classifier: Topic :: Text Processing :: Markup :: HTML
Classifier: License :: OSI Approved :: MIT License
Classifier: Programming Language :: Python :: 2
Classifier: Programming Language :: Python :: 2.7
Classifier: Programming Language :: Python :: 3
Classifier: Programming Language :: Python :: 3.3
Classifier: Programming Language :: Python :: 3.4
Classifier: Programming Language :: Python :: 3.5
Classifier: Programming Language :: Python :: 3.6
Classifier: Programming Language :: Python :: 3.7
Classifier: Programming Language :: Python :: 3.8
Classifier: Programming Language :: Python :: 3.9
Requires-Dist: jupyter (>=1.0)
